{
  "attr-spacing": "warn",
  "close-attr": "error",
  "close-order": "error",
  "deprecated": "warn",
  "doctype-html": "warn",
  "element-name": "error",
  "meta-refresh": "warn",
  "no-conditional-comment": "warn",
  "no-deprecated-attr": "warn",
  "no-dup-attr": "error",
  "no-dup-class": "error",
  "no-dup-id": "error",
  "no-raw-characters": "error",
  "no-redundant-for": "warn",
  "no-redundant-role": "warn",
  "unrecognized-char-ref": "warn",
  "attribute-allowed-values": "warn",
  "element-permitted-content": "warn",
  "element-permitted-occurrences": "warn",
  "element-permitted-order": "warn",
  "element-required-attributes": "warn",
  "input-attributes": "warn",
  "no-multiple-main": "warn",
  "script-element": "warn",
  "void-content": "warn",
  "aria-label-misuse": "warn",
  "empty-heading": "warn",
  "empty-title": "warn",
  "multiple-labeled-controls": "warn",
  "no-autoplay": "warn",
  "svg-focusable": "warn",
  "text-content": "warn",
  "wcag/h30": "warn",
  "wcag/h32": "warn",
  "wcag/h36": "warn",
  "wcag/h37": "warn",
  "wcag/h67": "warn",
  "wcag/h71": "warn",
  "no-trailing-whitespace": "warn",
  "no-missing-references": "warn",
  "no-utf8-bom": "warn"
}